py_cn_phone_area_code/__init__.py
py_cn_phone_area_code/skeleton.py
py_cn_phone_area_code-1.0.5.dist-info/DESCRIPTION.rst
py_cn_phone_area_code-1.0.5.dist-info/METADATA
py_cn_phone_area_code-1.0.5.dist-info/RECORD
py_cn_phone_area_code-1.0.5.dist-info/WHEEL
py_cn_phone_area_code-1.0.5.dist-info/metadata.json
py_cn_phone_area_code-1.0.5.dist-info/top_level.txt
