Metadata-Version: 2.0
Name: py-cn-phone-area-code
Version: 1.0.5
Summary: Python lib , convert phone to area code , or find area phone code
Home-page: https://github.com/netroby/py-cn-phone-area-code
Author: ZhiFeng Hu
Author-email: huzhifeng@douyu.tv
License: MIT
Platform: UNKNOWN
Classifier: Development Status :: 4 - Beta
Classifier: Programming Language :: Python
